{"_path":"/getting-started/options","_dir":"getting-started","_draft":false,"_partial":false,"_locale":"","_empty":false,"title":"Options","description":"Configure Vuxtify with the vuxtify property in your nuxt.config.ts file.","body":{"type":"root","children":[{"type":"element","tag":"h1","props":{"id":"options"},"children":[{"type":"text","value":"Options"}]},{"type":"element","tag":"p","props":{},"children":[{"type":"text","value":"Configure Vuxtify with the "},{"type":"element","tag":"code-inline","props":{},"children":[{"type":"text","value":"vuxtify"}]},{"type":"text","value":" property in your "},{"type":"element","tag":"code-inline","props":{},"children":[{"type":"text","value":"nuxt.config.ts"}]},{"type":"text","value":" file."}]},{"type":"element","tag":"code","props":{"code":"export default defineNuxtConfig({\r\n  vuxtify: {\r\n    // Default Options\r\n    treeShaking: false,\r\n    compressAssets: false,\r\n    debug: false,\r\n  }\r\n})\n","filename":"nuxt.config.ts","language":"js","meta":"[nuxt.config.ts]"},"children":[{"type":"element","tag":"pre","props":{},"children":[{"type":"element","tag":"code","props":{"__ignoreMap":""},"children":[{"type":"element","tag":"span","props":{"class":"line","line":1},"children":[{"type":"element","tag":"span","props":{"class":"ct-cf99fc"},"children":[{"type":"text","value":"export"}]},{"type":"element","tag":"span","props":{"class":"ct-bbd194"},"children":[{"type":"text","value":" "}]},{"type":"element","tag":"span","props":{"class":"ct-cf99fc"},"children":[{"type":"text","value":"default"}]},{"type":"element","tag":"span","props":{"class":"ct-bbd194"},"children":[{"type":"text","value":" "}]},{"type":"element","tag":"span","props":{"class":"ct-97d5e9"},"children":[{"type":"text","value":"defineNuxtConfig"}]},{"type":"element","tag":"span","props":{"class":"ct-bbd194"},"children":[{"type":"text","value":"({\n"}]}]},{"type":"element","tag":"span","props":{"class":"line","line":2},"children":[{"type":"element","tag":"span","props":{"class":"ct-bbd194"},"children":[{"type":"text","value":"  "}]},{"type":"element","tag":"span","props":{"class":"ct-4ca340"},"children":[{"type":"text","value":"vuxtify: {\n"}]}]},{"type":"element","tag":"span","props":{"class":"line","line":3},"children":[{"type":"element","tag":"span","props":{"class":"ct-4ca340"},"children":[{"type":"text","value":"    "}]},{"type":"element","tag":"span","props":{"class":"ct-565457"},"children":[{"type":"text","value":"// Default Options\n"}]}]},{"type":"element","tag":"span","props":{"class":"line","line":4},"children":[{"type":"element","tag":"span","props":{"class":"ct-4ca340"},"children":[{"type":"text","value":"    treeShaking: "}]},{"type":"element","tag":"span","props":{"class":"ct-adccc5"},"children":[{"type":"text","value":"false"}]},{"type":"element","tag":"span","props":{"class":"ct-4ca340"},"children":[{"type":"text","value":",\n"}]}]},{"type":"element","tag":"span","props":{"class":"line","line":5},"children":[{"type":"element","tag":"span","props":{"class":"ct-4ca340"},"children":[{"type":"text","value":"    compressAssets: "}]},{"type":"element","tag":"span","props":{"class":"ct-adccc5"},"children":[{"type":"text","value":"false"}]},{"type":"element","tag":"span","props":{"class":"ct-4ca340"},"children":[{"type":"text","value":",\n"}]}]},{"type":"element","tag":"span","props":{"class":"line","line":6},"children":[{"type":"element","tag":"span","props":{"class":"ct-4ca340"},"children":[{"type":"text","value":"    debug: "}]},{"type":"element","tag":"span","props":{"class":"ct-adccc5"},"children":[{"type":"text","value":"false"}]},{"type":"element","tag":"span","props":{"class":"ct-4ca340"},"children":[{"type":"text","value":",\n"}]}]},{"type":"element","tag":"span","props":{"class":"line","line":7},"children":[{"type":"element","tag":"span","props":{"class":"ct-4ca340"},"children":[{"type":"text","value":"  }\n"}]}]},{"type":"element","tag":"span","props":{"class":"line","line":8},"children":[{"type":"element","tag":"span","props":{"class":"ct-bbd194"},"children":[{"type":"text","value":"})"}]}]}]}]}]},{"type":"element","tag":"h2","props":{"id":"treeshaking"},"children":[{"type":"element","tag":"code-inline","props":{},"children":[{"type":"text","value":"treeShaking"}]}]},{"type":"element","tag":"ul","props":{},"children":[{"type":"element","tag":"li","props":{},"children":[{"type":"text","value":"Type: "},{"type":"element","tag":"code-inline","props":{},"children":[{"type":"text","value":"boolean"}]},{"type":"text","value":" | "},{"type":"element","tag":"code-inline","props":{},"children":[{"type":"text","value":"object"}]}]},{"type":"element","tag":"li","props":{},"children":[{"type":"text","value":"Default: "},{"type":"element","tag":"code-inline","props":{},"children":[{"type":"text","value":"false"}]}]}]},{"type":"element","tag":"p","props":{},"children":[{"type":"text","value":"Enables automatic tree shaking for Vuetify, using the method described in the "},{"type":"element","tag":"a","props":{"href":"https://vuetifyjs.com/en/features/treeshaking/","rel":["nofollow"]},"children":[{"type":"text","value":"Vuetify Docs"}]},{"type":"text","value":"."}]},{"type":"element","tag":"p","props":{},"children":[{"type":"text","value":"Depending on the "},{"type":"element","tag":"code-inline","props":{},"children":[{"type":"text","value":"build"}]},{"type":"text","value":" property defined in your "},{"type":"element","tag":"code-inline","props":{},"children":[{"type":"text","value":"nuxt.config.ts"}]},{"type":"text","value":" file (either "},{"type":"element","tag":"code-inline","props":{},"children":[{"type":"text","value":"vite"}]},{"type":"text","value":" or "},{"type":"element","tag":"code-inline","props":{},"children":[{"type":"text","value":"webpack"}]},{"type":"text","value":"), the appropriate Vuetify build plugin will be used with the provided options."}]},{"type":"element","tag":"alert","props":{"type":"info"},"children":[{"type":"element","tag":"p","props":{},"children":[{"type":"text","value":"If your project is missing the appropriate dependencies, for your build tool, the module will prompt you to install them."}]}]},{"type":"element","tag":"h2","props":{"id":"compressassets"},"children":[{"type":"element","tag":"code-inline","props":{},"children":[{"type":"text","value":"compressAssets"}]}]},{"type":"element","tag":"ul","props":{},"children":[{"type":"element","tag":"li","props":{},"children":[{"type":"text","value":"Type: "},{"type":"element","tag":"code-inline","props":{},"children":[{"type":"text","value":"boolean"}]}]},{"type":"element","tag":"li","props":{},"children":[{"type":"text","value":"Default: "},{"type":"element","tag":"code-inline","props":{},"children":[{"type":"text","value":"false"}]}]}]},{"type":"element","tag":"p","props":{},"children":[{"type":"text","value":"Compresses your nuxt assets by enabling nitro's "},{"type":"element","tag":"code-inline","props":{},"children":[{"type":"text","value":"compressPublicAssets"}]},{"type":"text","value":" option. This helps your project perform better in light house audits."}]},{"type":"element","tag":"h2","props":{"id":"debug"},"children":[{"type":"element","tag":"code-inline","props":{},"children":[{"type":"text","value":"debug"}]}]},{"type":"element","tag":"ul","props":{},"children":[{"type":"element","tag":"li","props":{},"children":[{"type":"text","value":"Type: "},{"type":"element","tag":"code-inline","props":{},"children":[{"type":"text","value":"boolean"}]}]},{"type":"element","tag":"li","props":{},"children":[{"type":"text","value":"Default: "},{"type":"element","tag":"code-inline","props":{},"children":[{"type":"text","value":"false"}]}]}]},{"type":"element","tag":"p","props":{},"children":[{"type":"text","value":"Enables the modules debug logger. This will log information about the module's behavior to the console."}]},{"type":"element","tag":"style","children":[{"type":"text","value":".ct-adccc5{color:#0550AE}\n.ct-565457{color:#6E7781}\n.ct-4ca340{color:#24292F}\n.ct-97d5e9{color:#8250DF}\n.ct-bbd194{color:#953800}\n.ct-cf99fc{color:#CF222E}\n.dark .ct-cf99fc{color:#FF7B72}\n.dark .ct-bbd194{color:#FFA657}\n.dark .ct-97d5e9{color:#D2A8FF}\n.dark .ct-4ca340{color:#C9D1D9}\n.dark .ct-565457{color:#8B949E}\n.dark .ct-adccc5{color:#79C0FF}"}]}],"toc":{"title":"","searchDepth":2,"depth":2,"links":[{"id":"treeshaking","depth":2,"text":"treeShaking"},{"id":"compressassets","depth":2,"text":"compressAssets"},{"id":"debug","depth":2,"text":"debug"}]}},"_type":"markdown","_id":"content:1.getting-started:1.options.md","_source":"content","_file":"1.getting-started/1.options.md","_extension":"md"}