[{"title":"Getting Started","_path":"/getting-started","children":[{"title":"Setup","_path":"/getting-started"},{"title":"Options","_path":"/getting-started/options"}]},{"title":"Features","_path":"/features","children":[{"title":"Composables","_path":"/features/composables"},{"title":"Providers","_path":"/features/providers"},{"title":"Custom SASS variables","_path":"/features/sass"}]},{"title":"Examples","_path":"/examples","children":[{"title":"Basic Usage","_path":"/examples/basic-usage"},{"title":"Optimized For Performance","_path":"/examples/optimized"}]}]